crypto_chassis_trade/__init__.py
crypto_chassis_trade/core/__init__.py
crypto_chassis_trade/core/exchanges/__init__.py
crypto_chassis_trade/core/exchanges/exchange_base.py
crypto_chassis_trade/core/exchanges/exchange_interface.py
crypto_chassis_trade/core/exchanges/okx.py
crypto_chassis_trade/core/models/__init__.py
crypto_chassis_trade/core/models/balance.py
crypto_chassis_trade/core/models/bbo.py
crypto_chassis_trade/core/models/fill.py
crypto_chassis_trade/core/models/instrument_information.py
crypto_chassis_trade/core/models/model_base.py
crypto_chassis_trade/core/models/ohlcv.py
crypto_chassis_trade/core/models/order.py
crypto_chassis_trade/core/models/position.py
crypto_chassis_trade/core/models/trade.py
crypto_chassis_trade/core/network/rest_request.py
crypto_chassis_trade/core/network/rest_response.py
crypto_chassis_trade/core/network/websocket_connection.py
crypto_chassis_trade/core/network/websocket_message.py
crypto_chassis_trade/core/network/websocket_request.py
crypto_chassis_trade/utility/helper.py
crypto_chassis_trade/utility/logger.py
crypto_chassis_trade/utility/logger_interface.py
crypto_chassis_trade-2.0.2.dist-info/LICENSE
crypto_chassis_trade-2.0.2.dist-info/METADATA
crypto_chassis_trade-2.0.2.dist-info/WHEEL
crypto_chassis_trade-2.0.2.dist-info/top_level.txt
crypto_chassis_trade-2.0.2.dist-info/RECORD
