Metadata-Version: 2.1
Name: crypto-chassis-trade
Version: 2.0.2
License: MIT License
Project-URL: Repository, https://github.com/chassis-community/test_2.git
Requires-Python: >=3.10
License-File: LICENSE
Requires-Dist: aiohttp[speedups]~=3.10
Requires-Dist: StrEnum~=0.4; python_version < "3.11"
Provides-Extra: dev
Requires-Dist: StrEnum; extra == "dev"
Requires-Dist: black; extra == "dev"
Requires-Dist: isort; extra == "dev"
Requires-Dist: autoflake; extra == "dev"
Requires-Dist: flake8; extra == "dev"
Requires-Dist: mypy; extra == "dev"
Requires-Dist: pylint; extra == "dev"
Requires-Dist: pytest; extra == "dev"
Requires-Dist: orjson; extra == "dev"
Requires-Dist: uvloop; platform_system != "Windows" and extra == "dev"
